gputree/__init__.py
gputree/app.py
gputree/cli.py
gputree/model.py
gputree/utils.py
gputree/view.py
gputree-0.1.0.dist-info/LICENSE
gputree-0.1.0.dist-info/METADATA
gputree-0.1.0.dist-info/WHEEL
gputree-0.1.0.dist-info/entry_points.txt
gputree-0.1.0.dist-info/top_level.txt
gputree-0.1.0.dist-info/RECORD
