Metadata-Version: 2.1
Name: gputree
Version: 0.1.0
Summary: Remote GPUs Monitoring.
Home-page: https://github.com/thmslmr/gputree
Author: Thomas Le Meur
Author-email: thmslmr@gmail.com
License: MIT
Platform: UNKNOWN
Classifier: License :: OSI Approved :: MIT License
Classifier: Natural Language :: English
Classifier: Programming Language :: Python
Classifier: Programming Language :: Python :: 3.6
Classifier: Topic :: Software Development :: Libraries :: Python Modules
Classifier: Topic :: Utilities
Classifier: Environment :: Console
Classifier: Intended Audience :: Developers
Requires-Python: >=3.5.0
Requires-Dist: asyncssh
Requires-Dist: blessings
Requires-Dist: pyyaml
